wdtagger/__init__.py
wdtagger/__main__.py
wdtagger/assets/selected_tags.csv
wdtagger-0.16.0.dist-info/METADATA
wdtagger-0.16.0.dist-info/WHEEL
wdtagger-0.16.0.dist-info/RECORD
