Metadata-Version: 2.4
Name: wdtagger
Version: 0.16.0
Summary: A simple and easy-to-use wrapper for the tagger model created by [SmilingWolf](https://github.com/SmilingWolf) which is specifically designed for tagging anime illustrations.
Author-email: Jianqi Pan <jannchie@gmail.com>
Requires-Python: >=3.10
Requires-Dist: huggingface-hub>=0.26.2
Requires-Dist: pandas>=2.2.3
Requires-Dist: pillow>=11.0.0
Provides-Extra: cpu
Requires-Dist: timm>=1.0.11; extra == 'cpu'
Requires-Dist: torch>=2.0.0; extra == 'cpu'
Requires-Dist: torchvision>=0.20.1; extra == 'cpu'
Provides-Extra: cuda11
Requires-Dist: timm>=1.0.11; extra == 'cuda11'
Requires-Dist: torch>=2.0.0; extra == 'cuda11'
Requires-Dist: torchvision>=0.20.1; extra == 'cuda11'
Provides-Extra: cuda12
Requires-Dist: timm>=1.0.11; extra == 'cuda12'
Requires-Dist: torch>=2.0.0; extra == 'cuda12'
Requires-Dist: torchvision>=0.20.1; extra == 'cuda12'
Provides-Extra: gpu
Requires-Dist: timm>=1.0.11; extra == 'gpu'
Requires-Dist: torch>=2.0.0; extra == 'gpu'
Requires-Dist: torchvision>=0.20.1; extra == 'gpu'
